simplerecommender.py
simplerecommender-0.0.2.dist-info/METADATA
simplerecommender-0.0.2.dist-info/WHEEL
simplerecommender-0.0.2.dist-info/top_level.txt
simplerecommender-0.0.2.dist-info/RECORD
