Metadata-Version: 2.1
Name: simplerecommender
Version: 0.0.2
Summary: Items recommendation for a specific user
Home-page: https://github.com/sujanshirol/simplerecommender
Author: Sujan Shirol
Author-email: <sshirol73@gmail.com>
License: UNKNOWN
Keywords: python,recommendation algorithm,recommender,recommendation
Platform: UNKNOWN
Classifier: Development Status :: 1 - Planning
Classifier: Intended Audience :: Developers
Classifier: Programming Language :: Python :: 3
Classifier: Operating System :: Unix
Classifier: Operating System :: MacOS :: MacOS X
Classifier: Operating System :: Microsoft :: Windows
